celery_decorator_taskcls.py
celery_decorator_taskcls-0.1.4.dist-info/LICENSE
celery_decorator_taskcls-0.1.4.dist-info/METADATA
celery_decorator_taskcls-0.1.4.dist-info/WHEEL
celery_decorator_taskcls-0.1.4.dist-info/top_level.txt
celery_decorator_taskcls-0.1.4.dist-info/zip-safe
celery_decorator_taskcls-0.1.4.dist-info/RECORD
